{
    "parameters": [
        {
            "expr": "56.5",
            "name": "Wp",
            "value": "56.5"
        },
        {
            "expr": "28.2",
            "name": "Lp",
            "value": "28.2"
        },
        {
            "expr": "2",
            "name": "Wf",
            "value": "2"
        },
        {
            "expr": "10.2",
            "name": "y0",
            "value": "10.2"
        },
        {
            "expr": "1.6",
            "name": "h",
            "value": "1.6"
        },
        {
            "expr": "0.035",
            "name": "tp",
            "value": "0.035"
        },
        {
            "expr": "6.86",
            "name": "k",
            "value": "6.86"
        },
        {
            "expr": "56.5",
            "name": "Wm",
            "value": "56.5"
        },
        {
            "expr": "1",
            "name": "Lm",
            "value": "1"
        }
    ],
    "version": 1
}