{
    "parameters": [
        {
            "expr": "36.07",
            "name": "Wp",
            "value": "36.07"
        },
        {
            "expr": "27.21",
            "name": "Lp",
            "value": "27.21"
        },
        {
            "expr": "5.54",
            "name": "Wf",
            "value": "5.54"
        },
        {
            "expr": "9.67",
            "name": "y0",
            "value": "9.67"
        },
        {
            "expr": "1.61",
            "name": "h",
            "value": "1.61"
        },
        {
            "expr": "0.035",
            "name": "tp",
            "value": "0.035"
        },
        {
            "expr": "6.86",
            "name": "k",
            "value": "6.86"
        }
    ],
    "version": 1
}